nvfuser_cu118_torch21-0.1.6.dev20240313.dist-info/entry_points.txt
nvfuser_cu118_torch21-0.1.6.dev20240313.dist-info/RECORD
nvfuser_cu118_torch21-0.1.6.dev20240313.dist-info/top_level.txt
nvfuser_cu118_torch21-0.1.6.dev20240313.dist-info/METADATA
nvfuser_cu118_torch21-0.1.6.dev20240313.dist-info/WHEEL
nvfuser_cu118_torch21-0.1.6.dev20240313.dist-info/LICENSE
nvfuser_python_utils/patch_nvfuser.py
nvfuser_python_utils/__init__.py
nvfuser/_C.cpython-310-x86_64-linux-gnu.so
nvfuser/__init__.pyi
nvfuser/pytorch_utils.py
nvfuser/utils.py
nvfuser/nvfuser_version.py
nvfuser/version.py
nvfuser/__init__.py
nvfuser/share/cmake/nvfuser/NvfuserConfig-release.cmake
nvfuser/share/cmake/nvfuser/NvfuserConfig.cmake
nvfuser/contrib/__init__.py
nvfuser/contrib/nn/normalization.py
nvfuser/contrib/nn/__init__.py
nvfuser/lib/libnvfuser_codegen.so
nvfuser/include/nvfuser/parallel_dimension_map.h
nvfuser/include/nvfuser/utils.h
nvfuser/include/nvfuser/non_divisible_split.h
nvfuser/include/nvfuser/codegen.h
nvfuser/include/nvfuser/partial_split_map.h
nvfuser/include/nvfuser/transform_rfactor.h
nvfuser/include/nvfuser/parallel_type_bitmap.h
nvfuser/include/nvfuser/vectorization_info.h
nvfuser/include/nvfuser/options.h
nvfuser/include/nvfuser/root_domain_map.h
nvfuser/include/nvfuser/cuda_utils.h
nvfuser/include/nvfuser/instrumentation.h
nvfuser/include/nvfuser/opaque_type.h
nvfuser/include/nvfuser/contiguity.h
nvfuser/include/nvfuser/executor_kernel_arg.h
nvfuser/include/nvfuser/executor.h
nvfuser/include/nvfuser/executor_params.h
nvfuser/include/nvfuser/tma.h
nvfuser/include/nvfuser/inlining.h
nvfuser/include/nvfuser/kernel_ir_dispatch.h
nvfuser/include/nvfuser/compute_at.h
nvfuser/include/nvfuser/exceptions.h
nvfuser/include/nvfuser/expr_evaluator.h
nvfuser/include/nvfuser/polymorphic_value.h
nvfuser/include/nvfuser/swizzle.h
nvfuser/include/nvfuser/dynamic_transform.h
nvfuser/include/nvfuser/kernel.h
nvfuser/include/nvfuser/mma_type.h
nvfuser/include/nvfuser/transform_view.h
nvfuser/include/nvfuser/struct.inl
nvfuser/include/nvfuser/type_promotion.h
nvfuser/include/nvfuser/validator_utils.h
nvfuser/include/nvfuser/debug.h
nvfuser/include/nvfuser/transform_iter.h
nvfuser/include/nvfuser/index_compute.h
nvfuser/include/nvfuser/type.h
nvfuser/include/nvfuser/grouped_reduction.h
